aftonfalk/__init__.py
aftonfalk/mssql/__init__.py
aftonfalk/mssql/column.py
aftonfalk/mssql/driver.py
aftonfalk/mssql/index.py
aftonfalk/mssql/path.py
aftonfalk/mssql/table.py
aftonfalk/mssql/timezone.py
aftonfalk/mssql/write_mode.py
aftonfalk-1.7.1.dist-info/LICENSE
aftonfalk-1.7.1.dist-info/METADATA
aftonfalk-1.7.1.dist-info/WHEEL
aftonfalk-1.7.1.dist-info/top_level.txt
aftonfalk-1.7.1.dist-info/RECORD
