Metadata-Version: 2.1
Name: aftonfalk
Version: 1.7.1
Summary: Makes it easier to interact with sql server using python
Author-email: Erik Bremstedt <erik.bremstedt@gmail.com>
Project-URL: Homepage, https://github.com/ebremstedt/aftonfalk
Project-URL: Issues, https://github.com/ebremstedt/aftonfalk/issues
Classifier: Programming Language :: Python :: 3
Classifier: License :: OSI Approved :: MIT License
Classifier: Operating System :: OS Independent
Requires-Python: >=3.8
License-File: LICENSE
Requires-Dist: pendulum==3.0.0
Requires-Dist: pyodbc==5.1.0
